agent_gateway/__init__.py
agent_gateway/gateway/__init__.py
agent_gateway/gateway/constants.py
agent_gateway/gateway/gateway.py
agent_gateway/gateway/output_parser.py
agent_gateway/gateway/planner.py
agent_gateway/gateway/task_processor.py
agent_gateway/tools/__init__.py
agent_gateway/tools/base.py
agent_gateway/tools/logger.py
agent_gateway/tools/schema.py
agent_gateway/tools/snowflake_prompts.py
agent_gateway/tools/snowflake_tools.py
agent_gateway/tools/tools.py
agent_gateway/tools/utils.py
agent_gateway/tools/data/sec_chunk_search.parquet
agent_gateway/tools/data/sp500.parquet
agent_gateway/tools/data/sp500_semantic_model.yaml
orchestration_framework-1.1.1.dist-info/METADATA
orchestration_framework-1.1.1.dist-info/WHEEL
orchestration_framework-1.1.1.dist-info/licenses/LICENSE
orchestration_framework-1.1.1.dist-info/RECORD
