Metadata-Version: 2.4
Name: orchestration-framework
Version: 1.1.1
Summary: A multi-agent framework with native support for Snowflake services
Project-URL: Repository, https://github.com/Snowflake-Labs/orchestration-framework.git
Project-URL: Issues, https://github.com/Snowflake-Labs/orchestration-framework/issues
Author-email: Alejandro Herrera <alejandro.herrera@snowflake.com>
Maintainer-email: Alejandro Herrera <alejandro.herrera@snowflake.com>, Tyler White <tyler.white@snowflake.com>
License:                                  Apache License
License-File: LICENSE
Requires-Python: >=3.9
Requires-Dist: aiohttp<4.0,>=3.10.9
Requires-Dist: asyncio>=3.4.3
Requires-Dist: pydantic<3.0,>=2.9.2
Requires-Dist: snowflake-snowpark-python[pandas]<2.0,>=1.22.1
Provides-Extra: dev
Requires-Dist: coverage<8.0,>=7.6.9; extra == 'dev'
Requires-Dist: ipython>=8.18.1; extra == 'dev'
Requires-Dist: pre-commit<5.0,>=4.0.1; extra == 'dev'
Requires-Dist: pytest<9.0,>=8.3.3; extra == 'dev'
Requires-Dist: python-dotenv>=1.1.0; extra == 'dev'
Requires-Dist: ruff<1.0,>=0.6.9; extra == 'dev'
Provides-Extra: fastmcp
Requires-Dist: fastmcp>=2.3.0; extra == 'fastmcp'
Provides-Extra: streamlit
Requires-Dist: python-dotenv>=1.0.1; extra == 'streamlit'
Requires-Dist: streamlit<2.0,>=1.39.0; extra == 'streamlit'
Provides-Extra: trulens
Requires-Dist: trulens-connectors-snowflake; extra == 'trulens'
Requires-Dist: trulens>=1.4.5; extra == 'trulens'
